{
  "_fv": 60,
  "_type": "tool",
  "definition": {
    "toolType": "Axe",
    "renderType": 0,
    "blockingRenderType": 0,
    "texture": "stone_halberd",
    "customModelName": "Normal",
    "blockingModelName": "Normal blocking",
    "name": "Stone halberd",
    "specialInformation": {
      "fixedValue": []
    },
    "creativeTab": {
      "value": "CUSTOM:GunsmithCognitisMelee"
    },
    "harvestLevel": 1,
    "efficiency": 4.0,
    "attackSpeed": 0.6,
    "enchantability": 5,
    "damageVsEntity": 5.5,
    "usageCount": 131,
    "blocksAffected": [],
    "repairItems": [
      {
        "value": "Blocks.COBBLESTONE"
      },
      {
        "value": "Blocks.STONE#0"
      }
    ],
    "immuneToFire": false,
    "stayInGridWhenCrafting": false,
    "damageOnCrafting": false
  }
}